eda_module/__init__.py
eda_module/dashboard.py
eda_module/eda.py
eda_module/eda_visualization.py
eda_module-0.1.2.dist-info/LICENSE
eda_module-0.1.2.dist-info/METADATA
eda_module-0.1.2.dist-info/WHEEL
eda_module-0.1.2.dist-info/entry_points.txt
eda_module-0.1.2.dist-info/top_level.txt
eda_module-0.1.2.dist-info/RECORD
