Metadata-Version: 2.1
Name: eda_module
Version: 0.1.2
Summary: A package for EDA with Streamlit dashboard
Author: Jhansi Siriprolu
Author-email: siriprolu2018@gmail.com
Classifier: Programming Language :: Python :: 3
Classifier: License :: OSI Approved :: MIT License
License-File: LICENSE
Requires-Dist: pandas
Requires-Dist: matplotlib
Requires-Dist: seaborn
Requires-Dist: plotly
Requires-Dist: streamlit
